profyle/__init__.py
profyle/application/__init__.py
profyle/application/profyle.py
profyle/application/trace/__init__.py
profyle/application/trace/create.py
profyle/application/trace/delete.py
profyle/application/trace/get.py
profyle/application/trace/store.py
profyle/application/trace/vacuum.py
profyle/django.py
profyle/domain/__init__.py
profyle/domain/trace.py
profyle/domain/trace_repository.py
profyle/fastapi.py
profyle/flask.py
profyle/infrastructure/__init__.py
profyle/infrastructure/http_server.py
profyle/infrastructure/middleware/__init__.py
profyle/infrastructure/middleware/django.py
profyle/infrastructure/middleware/fastapi.py
profyle/infrastructure/middleware/flask.py
profyle/infrastructure/sqlite3/get_connection.py
profyle/infrastructure/sqlite3/repository.py
profyle/infrastructure/web/static/libs/tailwind.js
profyle/infrastructure/web/templates/traces.html
profyle/main.py
profyle/settings.py
profyle-0.3.0.dist-info/LICENSE
profyle-0.3.0.dist-info/METADATA
profyle-0.3.0.dist-info/WHEEL
profyle-0.3.0.dist-info/entry_points.txt
profyle-0.3.0.dist-info/RECORD
