Metadata-Version: 2.1
Name: profyle
Version: 0.3.0
Summary: Profyle, a development tool for analysing and managing python traces
Home-page: https://github.com/vpcarlos/profyle
License: MIT
Keywords: cprofile,devtool,perffeto,profyle,viztracer,fastapi,flask
Author: Carlos Valdivia
Author-email: vpcarlos97@gmail.com
Maintainer: Carlos Valdivia
Maintainer-email: vpcarlos97@gmail.com
Requires-Python: >=3.9,<4.0
Classifier: Environment :: Web Environment
Classifier: Framework :: FastAPI
Classifier: Framework :: Flask
Classifier: Intended Audience :: Developers
Classifier: Intended Audience :: Information Technology
Classifier: Intended Audience :: System Administrators
Classifier: License :: OSI Approved :: MIT License
Classifier: Operating System :: OS Independent
Classifier: Programming Language :: Python
Classifier: Programming Language :: Python :: 3
Classifier: Programming Language :: Python :: 3.9
Classifier: Programming Language :: Python :: 3.10
Classifier: Programming Language :: Python :: 3.11
Classifier: Programming Language :: Python :: 3.12
Classifier: Topic :: Internet
Classifier: Topic :: Software Development
Classifier: Topic :: Software Development :: Debuggers
Classifier: Topic :: Software Development :: Libraries
Classifier: Topic :: Software Development :: Libraries :: Python Modules
Classifier: Topic :: Software Development :: Testing
Classifier: Typing :: Typed
Requires-Dist: fastapi (>=0.70.0)
Requires-Dist: jinja2 (>=3.1.2,<4.0.0)
Requires-Dist: pydantic-settings (>=2.0.3,<3.0.0)
Requires-Dist: typer[all] (>=0.7.0,<0.8.0)
Requires-Dist: uvicorn (>=0.20.0)
Requires-Dist: viztracer (>=0.16.0,<0.17.0)
Project-URL: Repository, https://github.com/vpcarlos/profyle
